[{
    "id": "BU00550017",
    "name": "Warstiens",
    "geoType": "BU",
    "gemeentecode": "0055",
    "wijkcode": "00",
    "buurtcode": "17",
    "polygon": [
        [
            53.166912,
            5.881827
        ],
        [
            53.161623,
            5.884216
        ],
        [
            53.16199,
            5.880348
        ],
        [
            53.158486,
            5.881369
        ],
        [
            53.158969,
            5.877038
        ],
        [
            53.160983,
            5.877133
        ],
        [
            53.161093,
            5.875969
        ],
        [
            53.15817,
            5.875718
        ],
        [
            53.158194,
            5.870906
        ],
        [
            53.159231,
            5.870806
        ],
        [
            53.15872,
            5.864286
        ],
        [
            53.156879,
            5.863113
        ],
        [
            53.157206,
            5.860667
        ],
        [
            53.158801,
            5.858523
        ],
        [
            53.156917,
            5.855299
        ],
        [
            53.158455,
            5.852965
        ],
        [
            53.165262,
            5.854844
        ],
        [
            53.166603,
            5.859815
        ],
        [
            53.165753,
            5.872463
        ],
        [
            53.167089,
            5.8717
        ],
        [
            53.166912,
            5.881827
        ]
    ]
,"aangrenzende":["BU00550016","BU00550018"]}]