[{
    "id": "BU00390100",
    "name": "Westerlee",
    "geoType": "BU",
    "gemeentecode": "0039",
    "wijkcode": "01",
    "buurtcode": "00",
    "polygon": [
        [
            53.142321,
            6.99229
        ],
        [
            53.137826,
            6.973751
        ],
        [
            53.137931,
            6.966711
        ],
        [
            53.136064,
            6.958567
        ],
        [
            53.134255,
            6.956482
        ],
        [
            53.134479,
            6.956389
        ],
        [
            53.135102,
            6.956411
        ],
        [
            53.1384,
            6.957858
        ],
        [
            53.140354,
            6.966696
        ],
        [
            53.143194,
            6.971796
        ],
        [
            53.148372,
            6.984903
        ],
        [
            53.151122,
            6.989241
        ],
        [
            53.154675,
            6.991987
        ],
        [
            53.155994,
            6.995791
        ],
        [
            53.153469,
            7.000527
        ],
        [
            53.152268,
            7.00293
        ],
        [
            53.149877,
            7.001896
        ],
        [
            53.145254,
            6.997463
        ],
        [
            53.142321,
            6.99229
        ]
    ]
,"aangrenzende":["BU00390002","BU00390003","BU00390005","BU00390108","BU00390109","BU19870209"]}]