[{
    "id": "BU00140906",
    "name": "Beijum-West",
    "geoType": "BU",
    "gemeentecode": "0014",
    "wijkcode": "09",
    "buurtcode": "06",
    "polygon": [
        [
            53.255664,
            6.587615
        ],
        [
            53.255579,
            6.587595
        ],
        [
            53.255549,
            6.590592
        ],
        [
            53.255507,
            6.590942
        ],
        [
            53.244108,
            6.598331
        ],
        [
            53.241557,
            6.592931
        ],
        [
            53.240947,
            6.593632
        ],
        [
            53.239356,
            6.589426
        ],
        [
            53.243104,
            6.583689
        ],
        [
            53.24699,
            6.581219
        ],
        [
            53.248196,
            6.578867
        ],
        [
            53.249788,
            6.580532
        ],
        [
            53.256481,
            6.587809
        ],
        [
            53.255664,
            6.587615
        ]
    ]
,"aangrenzende":["BU00050002","BU00050003","BU00140205","BU00140207","BU00140904","BU00140905","BU00140907"]}]