[{
    "id": "BU00250004",
    "name": "Boerakker",
    "geoType": "BU",
    "gemeentecode": "0025",
    "wijkcode": "00",
    "buurtcode": "04",
    "polygon": [
        [
            53.181323,
            6.3318
        ],
        [
            53.17999,
            6.329636
        ],
        [
            53.180998,
            6.327819
        ],
        [
            53.186603,
            6.326838
        ],
        [
            53.187698,
            6.322472
        ],
        [
            53.188702,
            6.321418
        ],
        [
            53.189699,
            6.321974
        ],
        [
            53.190493,
            6.325726
        ],
        [
            53.192535,
            6.328832
        ],
        [
            53.18855,
            6.332742
        ],
        [
            53.186222,
            6.333655
        ],
        [
            53.181323,
            6.3318
        ]
    ]
,"aangrenzende":["BU00250009"]}]