[{
    "id": "BU00480101",
    "name": "Wollinghuizen",
    "geoType": "BU",
    "gemeentecode": "0048",
    "wijkcode": "01",
    "buurtcode": "01",
    "polygon": [
        [
            52.991952,
            7.157103
        ],
        [
            52.990511,
            7.154008
        ],
        [
            52.990779,
            7.148914
        ],
        [
            52.992532,
            7.14653
        ],
        [
            52.994346,
            7.14598
        ],
        [
            52.996236,
            7.147544
        ],
        [
            52.997235,
            7.150603
        ],
        [
            52.995693,
            7.157111
        ],
        [
            52.991952,
            7.157103
        ]
    ]
,"aangrenzende":["BU00480109","BU00480209"]}]