[{
    "id": "BU00700006",
    "name": "Hamburgerrak en Het Want",
    "geoType": "BU",
    "gemeentecode": "0070",
    "wijkcode": "00",
    "buurtcode": "06",
    "polygon": [
        [
            53.199342,
            5.549988
        ],
        [
            53.19331,
            5.547851
        ],
        [
            53.193843,
            5.540768
        ],
        [
            53.197158,
            5.541196
        ],
        [
            53.198796,
            5.54127
        ],
        [
            53.199342,
            5.549988
        ]
    ]
,"aangrenzende":["BU00700001","BU00700007","BU00700008","BU00700107","BU00700500","BU00700501"]}]