[{
    "id": "BU00802201",
    "name": "Vrijheidswijk-West",
    "geoType": "BU",
    "gemeentecode": "0080",
    "wijkcode": "22",
    "buurtcode": "01",
    "polygon": [
        [
            53.217581,
            5.814772
        ],
        [
            53.212599,
            5.81039
        ],
        [
            53.212709,
            5.803503
        ],
        [
            53.212884,
            5.802576
        ],
        [
            53.217477,
            5.80782
        ],
        [
            53.217755,
            5.808073
        ],
        [
            53.217634,
            5.811967
        ],
        [
            53.217581,
            5.814772
        ]
    ]
,"aangrenzende":["BU00802003","BU00802101","BU00802102","BU00802202","BU00802302","BU00802303","BU00803001","BU00803002"]}]