[{
    "id": "BU00580009",
    "name": "Dokkum Jantjeszeepolder",
    "geoType": "BU",
    "gemeentecode": "0058",
    "wijkcode": "00",
    "buurtcode": "09",
    "polygon": [
        [
            53.320076,
            5.996244
        ],
        [
            53.317745,
            5.997491
        ],
        [
            53.31803,
            6.005091
        ],
        [
            53.317184,
            6.008684
        ],
        [
            53.309446,
            6.009269
        ],
        [
            53.310343,
            5.9994
        ],
        [
            53.310372,
            5.993618
        ],
        [
            53.316142,
            5.991886
        ],
        [
            53.319129,
            5.989528
        ],
        [
            53.320076,
            5.996244
        ]
    ]
,"aangrenzende":["BU00580002","BU00580005","BU00580006","BU00580007","BU00580010"]}]