[{
    "id": "BU00470200",
    "name": "Wildervank",
    "geoType": "BU",
    "gemeentecode": "0047",
    "wijkcode": "02",
    "buurtcode": "00",
    "polygon": [
        [
            53.084725,
            6.886686
        ],
        [
            53.069687,
            6.87742
        ],
        [
            53.077421,
            6.866804
        ],
        [
            53.079668,
            6.855265
        ],
        [
            53.08729,
            6.859918
        ],
        [
            53.089297,
            6.862707
        ],
        [
            53.095805,
            6.866965
        ],
        [
            53.095602,
            6.871341
        ],
        [
            53.094971,
            6.872767
        ],
        [
            53.092373,
            6.876666
        ],
        [
            53.084725,
            6.886686
        ]
    ]
,"aangrenzende":["BU00470003","BU00470004","BU00470005","BU00470006","BU00470109","BU00470201","BU00470209"]}]