[{
    "id": "BU01770500",
    "name": "Mari_nheem-Kern",
    "geoType": "BU",
    "gemeentecode": "0177",
    "wijkcode": "05",
    "buurtcode": "00",
    "polygon": [
        [
            52.381912,
            6.327246
        ],
        [
            52.378401,
            6.327482
        ],
        [
            52.379673,
            6.316396
        ],
        [
            52.381978,
            6.316369
        ],
        [
            52.383552,
            6.314849
        ],
        [
            52.386602,
            6.321802
        ],
        [
            52.387088,
            6.326013
        ],
        [
            52.384189,
            6.324814
        ],
        [
            52.381979,
            6.325511
        ],
        [
            52.381912,
            6.327246
        ]
    ]
,"aangrenzende":["BU01770507","BU01770508"]}]