[{
    "id": "BU01141001",
    "name": "Oosterse Bos en Middendorp",
    "geoType": "BU",
    "gemeentecode": "0114",
    "wijkcode": "10",
    "buurtcode": "01",
    "polygon": [
        [
            52.659085,
            6.903628
        ],
        [
            52.657924,
            6.90689
        ],
        [
            52.658779,
            6.907713
        ],
        [
            52.654945,
            6.917119
        ],
        [
            52.65527,
            6.922284
        ],
        [
            52.654037,
            6.925987
        ],
        [
            52.650481,
            6.930548
        ],
        [
            52.64996,
            6.927379
        ],
        [
            52.652429,
            6.917645
        ],
        [
            52.653831,
            6.908252
        ],
        [
            52.658279,
            6.896224
        ],
        [
            52.661022,
            6.897609
        ],
        [
            52.664577,
            6.889883
        ],
        [
            52.666661,
            6.891839
        ],
        [
            52.662353,
            6.906798
        ],
        [
            52.659085,
            6.903628
        ]
    ]
,"aangrenzende":["BU01141000","BU01141009","BU01142109"]}]