[{
    "id": "BU01411402",
    "name": "Kerkelanden",
    "geoType": "BU",
    "gemeentecode": "0141",
    "wijkcode": "14",
    "buurtcode": "02",
    "polygon": [
        [
            52.356935,
            6.654149
        ],
        [
            52.35588,
            6.653997
        ],
        [
            52.356127,
            6.647364
        ],
        [
            52.357398,
            6.647014
        ],
        [
            52.362042,
            6.645493
        ],
        [
            52.358206,
            6.652459
        ],
        [
            52.356935,
            6.654149
        ]
    ]
,"aangrenzende":["BU01411400","BU01411401","BU01411403","BU01411404"]}]