[{
    "id": "BU01094045",
    "name": "Verspreide huizen t Haantje",
    "geoType": "BU",
    "gemeentecode": "0109",
    "wijkcode": "40",
    "buurtcode": "45",
    "polygon": [
        [
            52.80673,
            6.806697
        ],
        [
            52.806526,
            6.809443
        ],
        [
            52.814018,
            6.821745
        ],
        [
            52.81429,
            6.836437
        ],
        [
            52.814198,
            6.836583
        ],
        [
            52.81055,
            6.840913
        ],
        [
            52.80505,
            6.84963
        ],
        [
            52.798796,
            6.846455
        ],
        [
            52.798564,
            6.846281
        ],
        [
            52.80031,
            6.83888
        ],
        [
            52.801529,
            6.839581
        ],
        [
            52.806332,
            6.826872
        ],
        [
            52.803883,
            6.816411
        ],
        [
            52.801906,
            6.810893
        ],
        [
            52.80065,
            6.811248
        ],
        [
            52.798189,
            6.80321
        ],
        [
            52.801305,
            6.800955
        ],
        [
            52.805069,
            6.803837
        ],
        [
            52.807642,
            6.797232
        ],
        [
            52.810649,
            6.793038
        ],
        [
            52.819904,
            6.827425
        ],
        [
            52.819697,
            6.827862
        ],
        [
            52.816205,
            6.8334
        ],
        [
            52.815853,
            6.818753
        ],
        [
            52.808941,
            6.807599
        ],
        [
            52.80673,
            6.806697
        ]
    ]
,"aangrenzende":["BU01094044","BU01094046","BU01094050","BU16811309"]}]