[{
    "id": "BU01660900",
    "name": "Verspreide huizen polder Mastenbroek",
    "geoType": "BU",
    "gemeentecode": "0166",
    "wijkcode": "09",
    "buurtcode": "00",
    "polygon": [
        [
            52.54535,
            6.00826
        ],
        [
            52.538867,
            5.983079
        ],
        [
            52.570578,
            5.958936
        ],
        [
            52.577541,
            5.983043
        ],
        [
            52.577942,
            5.983308
        ],
        [
            52.585876,
            6.01292
        ],
        [
            52.585876,
            6.012921
        ],
        [
            52.559701,
            6.033198
        ],
        [
            52.549971,
            6.003564
        ],
        [
            52.545454,
            6.007924
        ],
        [
            52.54535,
            6.00826
        ]
    ]
,"aangrenzende":["BU01660304","BU01660306","BU01660800","BU01932210","BU18960108","BU18960307"]}]