[{
    "id": "BU01600408",
    "name": "Verspreide huizen Sibculo",
    "geoType": "BU",
    "gemeentecode": "0160",
    "wijkcode": "04",
    "buurtcode": "08",
    "polygon": [
        [
            52.508851,
            6.599884
        ],
        [
            52.497991,
            6.625325
        ],
        [
            52.503887,
            6.645591
        ],
        [
            52.49526,
            6.658956
        ],
        [
            52.492403,
            6.663623
        ],
        [
            52.488183,
            6.653576
        ],
        [
            52.482776,
            6.654893
        ],
        [
            52.478361,
            6.647405
        ],
        [
            52.474719,
            6.651718
        ],
        [
            52.472938,
            6.650194
        ],
        [
            52.471257,
            6.641432
        ],
        [
            52.471234,
            6.641313
        ],
        [
            52.471296,
            6.635427
        ],
        [
            52.472241,
            6.631037
        ],
        [
            52.474085,
            6.626673
        ],
        [
            52.472271,
            6.62236
        ],
        [
            52.469699,
            6.616246
        ],
        [
            52.466134,
            6.613203
        ],
        [
            52.466979,
            6.611866
        ],
        [
            52.467048,
            6.611756
        ],
        [
            52.479736,
            6.601801
        ],
        [
            52.480695,
            6.595938
        ],
        [
            52.492242,
            6.609509
        ],
        [
            52.501439,
            6.589141
        ],
        [
            52.501524,
            6.588944
        ],
        [
            52.504223,
            6.592941
        ],
        [
            52.500538,
            6.601495
        ],
        [
            52.502071,
            6.603268
        ],
        [
            52.505608,
            6.594993
        ],
        [
            52.508186,
            6.598811
        ],
        [
            52.508851,
            6.599884
        ]
    ]
,"aangrenzende":["BU01600401","BU01600402","BU01600407","BU01600409","BU01600508","BU01750408","BU17000201","BU17000202","BU17000208","BU17000409"]}]