[{
    "id": "BU02960007",
    "name": "Industrieterrein Zesweg",
    "geoType": "BU",
    "gemeentecode": "0296",
    "wijkcode": "00",
    "buurtcode": "07",
    "polygon": [
        [
            51.820378,
            5.774254
        ],
        [
            51.814805,
            5.746834
        ],
        [
            51.817163,
            5.74435
        ],
        [
            51.819052,
            5.752822
        ],
        [
            51.82376,
            5.757534
        ],
        [
            51.822841,
            5.771635
        ],
        [
            51.820378,
            5.774254
        ]
    ]
,"aangrenzende":["BU02680739","BU02680849","BU02960004","BU02960101","BU02960104"]}]