[{
    "id": "BU03530014",
    "name": "Over Oudland",
    "geoType": "BU",
    "gemeentecode": "0353",
    "wijkcode": "00",
    "buurtcode": "14",
    "polygon": [
        [
            52.009721,
            5.064243
        ],
        [
            52.009156,
            5.061181
        ],
        [
            52.010579,
            5.060848
        ],
        [
            52.015006,
            5.056277
        ],
        [
            52.015483,
            5.06482
        ],
        [
            52.011125,
            5.06626
        ],
        [
            52.009721,
            5.064243
        ]
    ]
,"aangrenzende":["BU03530011","BU03530012","BU03530013","BU03530015","BU03530030"]}]