[{
    "id": "BU03440174",
    "name": "Halve Maan",
    "geoType": "BU",
    "gemeentecode": "0344",
    "wijkcode": "01",
    "buurtcode": "74",
    "polygon": [
        [
            52.082627,
            5.087555
        ],
        [
            52.081543,
            5.085347
        ],
        [
            52.082163,
            5.080244
        ],
        [
            52.097656,
            5.077196
        ],
        [
            52.094825,
            5.079967
        ],
        [
            52.092431,
            5.08428
        ],
        [
            52.090112,
            5.08272
        ],
        [
            52.085138,
            5.083605
        ],
        [
            52.082627,
            5.087555
        ]
    ]
,"aangrenzende":["BU03440172","BU03440173","BU03440178","BU03440179","BU03440982","BU03440986"]}]