[{
    "id": "BU03810104",
    "name": "Bredius-Oost",
    "geoType": "BU",
    "gemeentecode": "0381",
    "wijkcode": "01",
    "buurtcode": "04",
    "polygon": [
        [
            52.275602,
            5.174399
        ],
        [
            52.275361,
            5.173661
        ],
        [
            52.276191,
            5.17335
        ],
        [
            52.277737,
            5.17246
        ],
        [
            52.27905,
            5.176821
        ],
        [
            52.280866,
            5.175137
        ],
        [
            52.282804,
            5.175268
        ],
        [
            52.283525,
            5.177601
        ],
        [
            52.283527,
            5.177609
        ],
        [
            52.278147,
            5.184962
        ],
        [
            52.278145,
            5.184964
        ],
        [
            52.276988,
            5.180765
        ],
        [
            52.276635,
            5.178011
        ],
        [
            52.275602,
            5.174399
        ]
    ]
,"aangrenzende":["BU03810002","BU03810003","BU03810102","BU03810103","BU03810201","BU03810202","BU03810203","BU04060206","BU04250010","BU04250011"]}]