[{
    "id": "BU03010302",
    "name": "Braamkamp",
    "geoType": "BU",
    "gemeentecode": "0301",
    "wijkcode": "03",
    "buurtcode": "02",
    "polygon": [
        [
            52.121473,
            6.21045
        ],
        [
            52.120159,
            6.199897
        ],
        [
            52.123421,
            6.199796
        ],
        [
            52.124442,
            6.207655
        ],
        [
            52.121473,
            6.21045
        ]
    ]
,"aangrenzende":["BU03010300","BU03010301","BU03010303"]}]