[{
    "id": "BU04970413",
    "name": "Weijland",
    "geoType": "BU",
    "gemeentecode": "0497",
    "wijkcode": "04",
    "buurtcode": "13",
    "polygon": [
        [
            52.105125,
            4.822259
        ],
        [
            52.091801,
            4.82387
        ],
        [
            52.080123,
            4.825476
        ],
        [
            52.079734,
            4.825481
        ],
        [
            52.077975,
            4.817357
        ],
        [
            52.078074,
            4.812462
        ],
        [
            52.082178,
            4.802371
        ],
        [
            52.08593,
            4.795779
        ],
        [
            52.08588,
            4.791984
        ],
        [
            52.08451,
            4.78696
        ],
        [
            52.091907,
            4.785339
        ],
        [
            52.102076,
            4.785658
        ],
        [
            52.103602,
            4.792807
        ],
        [
            52.103722,
            4.796891
        ],
        [
            52.102661,
            4.813932
        ],
        [
            52.104995,
            4.818482
        ],
        [
            52.105125,
            4.822259
        ]
    ]
,"aangrenzende":["BU04970101","BU04970104","BU04970514","BU06320100","BU06320101"]}]