[{
    "id": "BU04780000",
    "name": "Beets",
    "geoType": "BU",
    "gemeentecode": "0478",
    "wijkcode": "00",
    "buurtcode": "00",
    "polygon": [
        [
            52.581371,
            4.962232
        ],
        [
            52.580446,
            4.954863
        ],
        [
            52.581339,
            4.953379
        ],
        [
            52.586732,
            4.953326
        ],
        [
            52.593836,
            4.948871
        ],
        [
            52.593906,
            4.948827
        ],
        [
            52.595709,
            4.950285
        ],
        [
            52.597665,
            5.004055
        ],
        [
            52.597724,
            5.008207
        ],
        [
            52.593459,
            5.007296
        ],
        [
            52.588214,
            4.979798
        ],
        [
            52.586703,
            4.977751
        ],
        [
            52.584987,
            4.9681
        ],
        [
            52.581371,
            4.962232
        ]
    ]
,"aangrenzende":["BU03700007","BU03700008","BU04780100","BU04780500","BU15980500"]}]