[{
    "id": "BU04980302",
    "name": "Hem",
    "geoType": "BU",
    "gemeentecode": "0498",
    "wijkcode": "03",
    "buurtcode": "02",
    "polygon": [
        [
            52.664927,
            5.187786
        ],
        [
            52.663049,
            5.187949
        ],
        [
            52.663697,
            5.196695
        ],
        [
            52.661005,
            5.196159
        ],
        [
            52.660559,
            5.197782
        ],
        [
            52.660203,
            5.192493
        ],
        [
            52.658847,
            5.18743
        ],
        [
            52.655702,
            5.183449
        ],
        [
            52.657895,
            5.180702
        ],
        [
            52.655271,
            5.169986
        ],
        [
            52.652973,
            5.169156
        ],
        [
            52.652741,
            5.167542
        ],
        [
            52.652802,
            5.167097
        ],
        [
            52.656595,
            5.167279
        ],
        [
            52.662711,
            5.184154
        ],
        [
            52.664987,
            5.184111
        ],
        [
            52.664927,
            5.187786
        ]
    ]
,"aangrenzende":["BU04980300","BU04980306","BU04980307","BU04980400"]}]