[{
    "id": "BU05051901",
    "name": "Handelskade en s-Gravendeelsedijk",
    "geoType": "BU",
    "gemeentecode": "0505",
    "wijkcode": "19",
    "buurtcode": "01",
    "polygon": [
        [
            51.802164,
            4.649235
        ],
        [
            51.800768,
            4.644298
        ],
        [
            51.801332,
            4.64362
        ],
        [
            51.800513,
            4.642094
        ],
        [
            51.798576,
            4.641301
        ],
        [
            51.79951,
            4.638268
        ],
        [
            51.804066,
            4.642028
        ],
        [
            51.805088,
            4.640667
        ],
        [
            51.809453,
            4.647566
        ],
        [
            51.809521,
            4.647673
        ],
        [
            51.807492,
            4.649708
        ],
        [
            51.80438,
            4.646775
        ],
        [
            51.802164,
            4.649235
        ]
    ]
,"aangrenzende":["BU05050201","BU05051900","BU05051902","BU05051903","BU05051904","BU05051906","BU06420701"]}]