[{
    "id": "BU05990324",
    "name": "Nieuwe Westen",
    "geoType": "BU",
    "gemeentecode": "0599",
    "wijkcode": "03",
    "buurtcode": "24",
    "polygon": [
        [
            51.908648,
            4.458069
        ],
        [
            51.908471,
            4.45571
        ],
        [
            51.909702,
            4.449592
        ],
        [
            51.916485,
            4.444226
        ],
        [
            51.918056,
            4.443379
        ],
        [
            51.921998,
            4.437108
        ],
        [
            51.922337,
            4.441148
        ],
        [
            51.92301,
            4.454775
        ],
        [
            51.922716,
            4.454826
        ],
        [
            51.9215,
            4.456189
        ],
        [
            51.914022,
            4.455598
        ],
        [
            51.909556,
            4.457584
        ],
        [
            51.908648,
            4.458069
        ]
    ]
,"aangrenzende":["BU05990113","BU05990119","BU05990320","BU05990322","BU05990323","BU05990325","BU05990532","BU05990558","BU05991853"]}]