[{
    "id": "BU05183284",
    "name": "Leyenburg",
    "geoType": "BU",
    "gemeentecode": "0518",
    "wijkcode": "32",
    "buurtcode": "84",
    "polygon": [
        [
            52.057376,
            4.275735
        ],
        [
            52.05418,
            4.269737
        ],
        [
            52.05432,
            4.269236
        ],
        [
            52.058548,
            4.264177
        ],
        [
            52.062517,
            4.259368
        ],
        [
            52.066887,
            4.270182
        ],
        [
            52.063011,
            4.273155
        ],
        [
            52.062262,
            4.274856
        ],
        [
            52.061301,
            4.282941
        ],
        [
            52.057376,
            4.275735
        ]
    ]
,"aangrenzende":["BU05181785","BU05181786","BU05181983","BU05182054","BU05183130","BU05183135","BU05183488","BU05183489","BU05183536"]}]