[{
    "id": "BU05051301",
    "name": "Mildenburg en omgeving",
    "geoType": "BU",
    "gemeentecode": "0505",
    "wijkcode": "13",
    "buurtcode": "01",
    "polygon": [
        [
            51.778002,
            4.676058
        ],
        [
            51.774853,
            4.675265
        ],
        [
            51.7746,
            4.674452
        ],
        [
            51.776771,
            4.663391
        ],
        [
            51.776746,
            4.659696
        ],
        [
            51.780358,
            4.662636
        ],
        [
            51.780383,
            4.663696
        ],
        [
            51.779011,
            4.663871
        ],
        [
            51.778002,
            4.676058
        ]
    ]
,"aangrenzende":["BU05051200","BU05051300","BU05051302","BU05051303","BU05051908","BU05051914","BU05059804"]}]