[{
    "id": "BU06640108",
    "name": "Industrieterrein Haven",
    "geoType": "BU",
    "gemeentecode": "0664",
    "wijkcode": "01",
    "buurtcode": "08",
    "polygon": [
        [
            51.509333,
            3.8939
        ],
        [
            51.509096,
            3.893114
        ],
        [
            51.509423,
            3.890799
        ],
        [
            51.519136,
            3.89158
        ],
        [
            51.519814,
            3.891949
        ],
        [
            51.516128,
            3.899905
        ],
        [
            51.509333,
            3.8939
        ]
    ]
,"aangrenzende":["BU06640101","BU06640102","BU06640105","BU06640106","BU06640109","BU06640209"]}]