[{
    "id": "BU06100007",
    "name": "Industrieterrein Nijverwaard",
    "geoType": "BU",
    "gemeentecode": "0610",
    "wijkcode": "00",
    "buurtcode": "07",
    "polygon": [
        [
            51.830273,
            4.775003
        ],
        [
            51.827595,
            4.773329
        ],
        [
            51.82883,
            4.76584
        ],
        [
            51.830143,
            4.75128
        ],
        [
            51.831438,
            4.745532
        ],
        [
            51.83306,
            4.749784
        ],
        [
            51.833527,
            4.756156
        ],
        [
            51.830273,
            4.775003
        ]
    ]
,"aangrenzende":["BU06100000","BU06100006","BU06100008","BU06100009"]}]