[{
    "id": "BU06060905",
    "name": "Buurt 95",
    "geoType": "BU",
    "gemeentecode": "0606",
    "wijkcode": "09",
    "buurtcode": "05",
    "polygon": [
        [
            51.939984,
            4.392075
        ],
        [
            51.9353,
            4.394447
        ],
        [
            51.936204,
            4.387449
        ],
        [
            51.937052,
            4.382988
        ],
        [
            51.938051,
            4.379404
        ],
        [
            51.941581,
            4.385063
        ],
        [
            51.94246,
            4.386595
        ],
        [
            51.940227,
            4.389008
        ],
        [
            51.939984,
            4.392075
        ]
    ]
,"aangrenzende":["BU06060701","BU06060705","BU06060706","BU06060802","BU06060803","BU06060906","BU06060909"]}]