[{
    "id": "BU06230200",
    "name": "Stolwijk",
    "geoType": "BU",
    "gemeentecode": "0623",
    "wijkcode": "02",
    "buurtcode": "00",
    "polygon": [
        [
            51.978792,
            4.768037
        ],
        [
            51.976096,
            4.771837
        ],
        [
            51.976485,
            4.774209
        ],
        [
            51.973801,
            4.778043
        ],
        [
            51.96915,
            4.780302
        ],
        [
            51.962697,
            4.783981
        ],
        [
            51.961352,
            4.775579
        ],
        [
            51.96607,
            4.772917
        ],
        [
            51.96746,
            4.770868
        ],
        [
            51.975797,
            4.765222
        ],
        [
            51.977868,
            4.762346
        ],
        [
            51.978566,
            4.765371
        ],
        [
            51.978792,
            4.768037
        ]
    ]
,"aangrenzende":["BU06230201","BU06230202","BU06230204","BU06230206","BU06230207","BU06230208"]}]