[{
    "id": "BU06640409",
    "name": "Verspreide huizen Kattendijke",
    "geoType": "BU",
    "gemeentecode": "0664",
    "wijkcode": "04",
    "buurtcode": "09",
    "polygon": [
        [
            51.526279,
            3.967552
        ],
        [
            51.520834,
            3.963398
        ],
        [
            51.506472,
            3.965289
        ],
        [
            51.505521,
            3.960996
        ],
        [
            51.50535,
            3.960604
        ],
        [
            51.50367,
            3.956732
        ],
        [
            51.49722,
            3.943971
        ],
        [
            51.496528,
            3.943336
        ],
        [
            51.509981,
            3.945236
        ],
        [
            51.513433,
            3.938462
        ],
        [
            51.518435,
            3.932358
        ],
        [
            51.519824,
            3.935554
        ],
        [
            51.521007,
            3.935009
        ],
        [
            51.523955,
            3.939501
        ],
        [
            51.522484,
            3.939493
        ],
        [
            51.521207,
            3.944379
        ],
        [
            51.521877,
            3.949243
        ],
        [
            51.524053,
            3.94745
        ],
        [
            51.524174,
            3.945097
        ],
        [
            51.526203,
            3.943517
        ],
        [
            51.528746,
            3.948736
        ],
        [
            51.53065,
            3.957325
        ],
        [
            51.529857,
            3.965999
        ],
        [
            51.528993,
            3.968909
        ],
        [
            51.527213,
            3.970406
        ],
        [
            51.526297,
            3.968993
        ],
        [
            51.526279,
            3.967552
        ]
    ]
,"aangrenzende":["BU06640209","BU06640308","BU06640400","BU06780009","BU06780109"]}]