[{
    "id": "BU07970409",
    "name": "Buitengebied Haarsteeg",
    "geoType": "BU",
    "gemeentecode": "0797",
    "wijkcode": "04",
    "buurtcode": "09",
    "polygon": [
        [
            51.726504,
            5.224322
        ],
        [
            51.726272,
            5.225074
        ],
        [
            51.727175,
            5.227966
        ],
        [
            51.723583,
            5.230873
        ],
        [
            51.71459,
            5.22801
        ],
        [
            51.710998,
            5.229469
        ],
        [
            51.710235,
            5.227424
        ],
        [
            51.709637,
            5.224039
        ],
        [
            51.713606,
            5.217257
        ],
        [
            51.714915,
            5.201719
        ],
        [
            51.713785,
            5.197046
        ],
        [
            51.713825,
            5.193523
        ],
        [
            51.711591,
            5.194256
        ],
        [
            51.710945,
            5.192861
        ],
        [
            51.709422,
            5.182761
        ],
        [
            51.709486,
            5.181628
        ],
        [
            51.710938,
            5.181572
        ],
        [
            51.710533,
            5.177114
        ],
        [
            51.719591,
            5.174473
        ],
        [
            51.720366,
            5.181343
        ],
        [
            51.721371,
            5.183741
        ],
        [
            51.72082,
            5.190284
        ],
        [
            51.719782,
            5.192094
        ],
        [
            51.720522,
            5.196127
        ],
        [
            51.72553,
            5.203252
        ],
        [
            51.73077,
            5.202563
        ],
        [
            51.734915,
            5.2045
        ],
        [
            51.734386,
            5.209137
        ],
        [
            51.734339,
            5.209118
        ],
        [
            51.728062,
            5.219277
        ],
        [
            51.726504,
            5.224322
        ]
    ]
,"aangrenzende":["BU07961205","BU07961206","BU07970200","BU07970400","BU07970504","BU07970509"]}]