[{
    "id": "BU07852027",
    "name": "Riel-Dorp",
    "geoType": "BU",
    "gemeentecode": "0785",
    "wijkcode": "20",
    "buurtcode": "27",
    "polygon": [
        [
            51.522801,
            5.025915
        ],
        [
            51.519933,
            5.021548
        ],
        [
            51.520177,
            5.020732
        ],
        [
            51.520694,
            5.018828
        ],
        [
            51.518302,
            5.016899
        ],
        [
            51.517631,
            5.018828
        ],
        [
            51.517117,
            5.015934
        ],
        [
            51.519727,
            5.015437
        ],
        [
            51.520274,
            5.017228
        ],
        [
            51.523087,
            5.01455
        ],
        [
            51.529588,
            5.022675
        ],
        [
            51.533154,
            5.027204
        ],
        [
            51.530033,
            5.030996
        ],
        [
            51.522801,
            5.025915
        ]
    ]
,"aangrenzende":["BU07851426","BU07852028","BU07852129","BU07852230","BU07852331","BU08550609"]}]