[{
    "id": "BU07380600",
    "name": "Babyloni_nbroek",
    "geoType": "BU",
    "gemeentecode": "0738",
    "wijkcode": "06",
    "buurtcode": "00",
    "polygon": [
        [
            51.74737,
            5.036616
        ],
        [
            51.744141,
            5.03792
        ],
        [
            51.742222,
            5.031539
        ],
        [
            51.740205,
            5.022066
        ],
        [
            51.74111,
            5.005665
        ],
        [
            51.742327,
            5.000528
        ],
        [
            51.74413,
            4.99701
        ],
        [
            51.747163,
            4.995572
        ],
        [
            51.745468,
            5.00452
        ],
        [
            51.745174,
            5.021862
        ],
        [
            51.745268,
            5.028052
        ],
        [
            51.74737,
            5.036616
        ]
    ]
,"aangrenzende":["BU07380309","BU07380409","BU07380609"]}]