[{
    "id": "BU07330100",
    "name": "Heukelum Oude Kern",
    "geoType": "BU",
    "gemeentecode": "0733",
    "wijkcode": "01",
    "buurtcode": "00",
    "polygon": [
        [
            51.874294,
            5.083346
        ],
        [
            51.87132,
            5.07717
        ],
        [
            51.874289,
            5.072709
        ],
        [
            51.874291,
            5.073497
        ],
        [
            51.876108,
            5.080746
        ],
        [
            51.87621,
            5.080909
        ],
        [
            51.874294,
            5.083346
        ]
    ]
,"aangrenzende":["BU05450006","BU07330101","BU07330109"]}]