[{
    "id": "BU07157000",
    "name": "Sas van Gent",
    "geoType": "BU",
    "gemeentecode": "0715",
    "wijkcode": "70",
    "buurtcode": "00",
    "polygon": [
        [
            51.232599,
            3.799934
        ],
        [
            51.232212,
            3.803924
        ],
        [
            51.235545,
            3.806211
        ],
        [
            51.235346,
            3.809095
        ],
        [
            51.231262,
            3.807917
        ],
        [
            51.227426,
            3.806777
        ],
        [
            51.224455,
            3.805894
        ],
        [
            51.224788,
            3.800992
        ],
        [
            51.224088,
            3.799277
        ],
        [
            51.223169,
            3.789372
        ],
        [
            51.23715,
            3.788885
        ],
        [
            51.237445,
            3.788875
        ],
        [
            51.237166,
            3.795427
        ],
        [
            51.232599,
            3.799934
        ]
    ]
,"aangrenzende":["BU07157200","BU07157400","BU07157500","BU07157900"]}]