[{
    "id": "BU07030100",
    "name": "Kruiningen",
    "geoType": "BU",
    "gemeentecode": "0703",
    "wijkcode": "01",
    "buurtcode": "00",
    "polygon": [
        [
            51.454293,
            4.031005
        ],
        [
            51.451793,
            4.033896
        ],
        [
            51.446327,
            4.044329
        ],
        [
            51.441738,
            4.034897
        ],
        [
            51.44453,
            4.034088
        ],
        [
            51.448475,
            4.025422
        ],
        [
            51.450853,
            4.024404
        ],
        [
            51.453879,
            4.026755
        ],
        [
            51.454029,
            4.028859
        ],
        [
            51.453579,
            4.02981
        ],
        [
            51.454293,
            4.031005
        ]
    ]
,"aangrenzende":["BU07030109"]}]