[{
    "id": "BU07970209",
    "name": "Verspreide huizen Vlijmen",
    "geoType": "BU",
    "gemeentecode": "0797",
    "wijkcode": "02",
    "buurtcode": "09",
    "polygon": [
        [
            51.704462,
            5.190411
        ],
        [
            51.694192,
            5.195199
        ],
        [
            51.695497,
            5.186129
        ],
        [
            51.697863,
            5.16703
        ],
        [
            51.70194,
            5.164872
        ],
        [
            51.704462,
            5.190411
        ]
    ]
,"aangrenzende":["BU07970009","BU07970109","BU07970200","BU07970201","BU07970300","BU07970301","BU07970400"]}]