[{
    "id": "BU08790300",
    "name": "Achtmaal",
    "geoType": "BU",
    "gemeentecode": "0879",
    "wijkcode": "03",
    "buurtcode": "00",
    "polygon": [
        [
            51.453248,
            4.587758
        ],
        [
            51.450917,
            4.581039
        ],
        [
            51.453218,
            4.578637
        ],
        [
            51.456815,
            4.585584
        ],
        [
            51.454442,
            4.588545
        ],
        [
            51.453248,
            4.587758
        ]
    ]
,"aangrenzende":["BU08790309"]}]