[{
    "id": "BU08240006",
    "name": "Omgeving George parklaan",
    "geoType": "BU",
    "gemeentecode": "0824",
    "wijkcode": "00",
    "buurtcode": "06",
    "polygon": [
        [
            51.584199,
            5.203337
        ],
        [
            51.58334,
            5.199385
        ],
        [
            51.585969,
            5.198171
        ],
        [
            51.586236,
            5.201947
        ],
        [
            51.584199,
            5.203337
        ]
    ]
,"aangrenzende":["BU08240000","BU08240001","BU08240005"]}]