[{
    "id": "BU09350601",
    "name": "Heugem",
    "geoType": "BU",
    "gemeentecode": "0935",
    "wijkcode": "06",
    "buurtcode": "01",
    "polygon": [
        [
            50.808081,
            5.70928
        ],
        [
            50.808116,
            5.696511
        ],
        [
            50.810824,
            5.692272
        ],
        [
            50.811113,
            5.692274
        ],
        [
            50.811412,
            5.693709
        ],
        [
            50.818488,
            5.696904
        ],
        [
            50.825431,
            5.697924
        ],
        [
            50.833848,
            5.697965
        ],
        [
            50.831111,
            5.712573
        ],
        [
            50.828799,
            5.712165
        ],
        [
            50.82681,
            5.713824
        ],
        [
            50.822395,
            5.71244
        ],
        [
            50.817873,
            5.708956
        ],
        [
            50.81727,
            5.706923
        ],
        [
            50.808112,
            5.709503
        ],
        [
            50.808096,
            5.70939
        ],
        [
            50.808081,
            5.70928
        ]
    ]
,"aangrenzende":["BU09050009","BU09350100","BU09350105","BU09350600"]}]