[{
    "id": "BU09710002",
    "name": "Nieuwdorp",
    "geoType": "BU",
    "gemeentecode": "0971",
    "wijkcode": "00",
    "buurtcode": "02",
    "polygon": [
        [
            50.956841,
            5.780918
        ],
        [
            50.955546,
            5.776012
        ],
        [
            50.955812,
            5.77112
        ],
        [
            50.956784,
            5.769842
        ],
        [
            50.955826,
            5.758958
        ],
        [
            50.95845,
            5.756966
        ],
        [
            50.962995,
            5.766472
        ],
        [
            50.966604,
            5.775588
        ],
        [
            50.967712,
            5.784456
        ],
        [
            50.959957,
            5.785753
        ],
        [
            50.956841,
            5.780918
        ]
    ]
,"aangrenzende":["BU09710000","BU09710005","BU09710100","BU09710101","BU18830507"]}]