[{
    "id": "BU09410007",
    "name": "Verspreide huizen Berg en Nederweerterdijk",
    "geoType": "BU",
    "gemeentecode": "0941",
    "wijkcode": "00",
    "buurtcode": "07",
    "polygon": [
        [
            51.347279,
            5.873839
        ],
        [
            51.330669,
            5.840744
        ],
        [
            51.33808,
            5.832138
        ],
        [
            51.347036,
            5.840838
        ],
        [
            51.349673,
            5.855937
        ],
        [
            51.351871,
            5.868531
        ],
        [
            51.347279,
            5.873839
        ]
    ]
,"aangrenzende":["BU07430109","BU07430809","BU09410000","BU09410008","BU09460209"]}]