[{
    "id": "BU09570301",
    "name": "Leeuwen",
    "geoType": "BU",
    "gemeentecode": "0957",
    "wijkcode": "03",
    "buurtcode": "01",
    "polygon": [
        [
            51.219059,
            5.991924
        ],
        [
            51.213844,
            6.000275
        ],
        [
            51.214796,
            6.001188
        ],
        [
            51.214411,
            6.003977
        ],
        [
            51.213958,
            6.00496
        ],
        [
            51.213208,
            6.00356
        ],
        [
            51.21202,
            6.00587
        ],
        [
            51.211379,
            6.01226
        ],
        [
            51.2067,
            6.007339
        ],
        [
            51.203314,
            6.003265
        ],
        [
            51.205862,
            6.004714
        ],
        [
            51.209089,
            6.00439
        ],
        [
            51.207587,
            6.001909
        ],
        [
            51.210131,
            5.998135
        ],
        [
            51.210789,
            5.995222
        ],
        [
            51.207861,
            5.993846
        ],
        [
            51.206147,
            5.994711
        ],
        [
            51.206217,
            5.991622
        ],
        [
            51.210851,
            5.99276
        ],
        [
            51.215103,
            5.991041
        ],
        [
            51.219059,
            5.991924
        ]
    ]
,"aangrenzende":["BU09570003","BU09570300","BU09570302","BU09570809"]}]