[{
    "id": "BU15070804",
    "name": "Tuinhaversveld",
    "geoType": "BU",
    "gemeentecode": "1507",
    "wijkcode": "08",
    "buurtcode": "04",
    "polygon": [
        [
            51.418859,
            6.140872
        ],
        [
            51.4178,
            6.135822
        ],
        [
            51.423868,
            6.13473
        ],
        [
            51.422674,
            6.136703
        ],
        [
            51.420784,
            6.143703
        ],
        [
            51.418859,
            6.140872
        ]
    ]
,"aangrenzende":["BU15070800","BU15070802","BU15070803","BU15070809"]}]