[{
    "id": "BU16760200",
    "name": "Zonnemaire",
    "geoType": "BU",
    "gemeentecode": "1676",
    "wijkcode": "02",
    "buurtcode": "00",
    "polygon": [
        [
            51.715769,
            3.947983
        ],
        [
            51.715007,
            3.949963
        ],
        [
            51.715201,
            3.951389
        ],
        [
            51.717138,
            3.953767
        ],
        [
            51.716079,
            3.956336
        ],
        [
            51.714398,
            3.95417
        ],
        [
            51.713388,
            3.954433
        ],
        [
            51.711904,
            3.959205
        ],
        [
            51.710683,
            3.957364
        ],
        [
            51.71152,
            3.954196
        ],
        [
            51.709456,
            3.952077
        ],
        [
            51.709348,
            3.949562
        ],
        [
            51.710209,
            3.946251
        ],
        [
            51.710843,
            3.94668
        ],
        [
            51.712063,
            3.946462
        ],
        [
            51.712821,
            3.944722
        ],
        [
            51.712583,
            3.94163
        ],
        [
            51.713984,
            3.942585
        ],
        [
            51.714295,
            3.94582
        ],
        [
            51.717315,
            3.945214
        ],
        [
            51.71757,
            3.947884
        ],
        [
            51.715769,
            3.947983
        ]
    ]
,"aangrenzende":["BU16760209"]}]