[{
    "id": "BU16811300",
    "name": "Klijndijk",
    "geoType": "BU",
    "gemeentecode": "1681",
    "wijkcode": "13",
    "buurtcode": "00",
    "polygon": [
        [
            52.838215,
            6.852779
        ],
        [
            52.836194,
            6.867365
        ],
        [
            52.834163,
            6.867526
        ],
        [
            52.828714,
            6.858559
        ],
        [
            52.817619,
            6.864561
        ],
        [
            52.817119,
            6.86181
        ],
        [
            52.827241,
            6.855502
        ],
        [
            52.822949,
            6.848846
        ],
        [
            52.823608,
            6.84791
        ],
        [
            52.82867,
            6.855886
        ],
        [
            52.831653,
            6.853302
        ],
        [
            52.837342,
            6.851647
        ],
        [
            52.838215,
            6.852779
        ]
    ]
,"aangrenzende":["BU16811009","BU16811209","BU16811309"]}]