[{
    "id": "BU16990420",
    "name": "Verspreide huizen Peest",
    "geoType": "BU",
    "gemeentecode": "1699",
    "wijkcode": "04",
    "buurtcode": "20",
    "polygon": [
        [
            53.064846,
            6.515174
        ],
        [
            53.056787,
            6.511982
        ],
        [
            53.046959,
            6.505761
        ],
        [
            53.039297,
            6.501303
        ],
        [
            53.037785,
            6.491772
        ],
        [
            53.038254,
            6.491509
        ],
        [
            53.041668,
            6.489599
        ],
        [
            53.041906,
            6.491086
        ],
        [
            53.043245,
            6.49048
        ],
        [
            53.05394,
            6.484035
        ],
        [
            53.052648,
            6.47852
        ],
        [
            53.058293,
            6.475125
        ],
        [
            53.061795,
            6.484872
        ],
        [
            53.062604,
            6.491169
        ],
        [
            53.064692,
            6.498331
        ],
        [
            53.066886,
            6.499757
        ],
        [
            53.068961,
            6.511315
        ],
        [
            53.071232,
            6.510292
        ],
        [
            53.073946,
            6.512254
        ],
        [
            53.073919,
            6.512372
        ],
        [
            53.07386,
            6.512424
        ],
        [
            53.072049,
            6.513869
        ],
        [
            53.064846,
            6.515174
        ]
    ]
,"aangrenzende":["BU16990330","BU16990370","BU16990390","BU16990430","BU17301009","BU17301509"]}]