[{
    "id": "BU16740702",
    "name": "Tolberg-Centrum",
    "geoType": "BU",
    "gemeentecode": "1674",
    "wijkcode": "07",
    "buurtcode": "02",
    "polygon": [
        [
            51.517518,
            4.438288
        ],
        [
            51.509894,
            4.439261
        ],
        [
            51.510005,
            4.441141
        ],
        [
            51.506594,
            4.436824
        ],
        [
            51.505893,
            4.431412
        ],
        [
            51.507337,
            4.430663
        ],
        [
            51.507656,
            4.425362
        ],
        [
            51.508894,
            4.42807
        ],
        [
            51.510895,
            4.432944
        ],
        [
            51.518825,
            4.433238
        ],
        [
            51.520335,
            4.437732
        ],
        [
            51.517518,
            4.438288
        ]
    ]
,"aangrenzende":["BU16740701","BU16740703","BU16740705","BU16740706","BU16740709","BU16740804"]}]