[{
    "id": "BU17141409",
    "name": "Verspreide huizen Waterlandkerkje",
    "geoType": "BU",
    "gemeentecode": "1714",
    "wijkcode": "14",
    "buurtcode": "09",
    "polygon": [
        [
            51.339804,
            3.550687
        ],
        [
            51.335681,
            3.553994
        ],
        [
            51.336916,
            3.55842
        ],
        [
            51.334301,
            3.563892
        ],
        [
            51.335361,
            3.571285
        ],
        [
            51.334046,
            3.578388
        ],
        [
            51.33117,
            3.574171
        ],
        [
            51.317444,
            3.582684
        ],
        [
            51.31354,
            3.582915
        ],
        [
            51.311463,
            3.587497
        ],
        [
            51.309017,
            3.59046
        ],
        [
            51.306207,
            3.588127
        ],
        [
            51.305721,
            3.589633
        ],
        [
            51.30528,
            3.589977
        ],
        [
            51.297936,
            3.580225
        ],
        [
            51.292655,
            3.587605
        ],
        [
            51.288994,
            3.583447
        ],
        [
            51.287153,
            3.580651
        ],
        [
            51.287985,
            3.576316
        ],
        [
            51.290613,
            3.57191
        ],
        [
            51.291512,
            3.571875
        ],
        [
            51.295848,
            3.561663
        ],
        [
            51.294905,
            3.558832
        ],
        [
            51.291288,
            3.557542
        ],
        [
            51.290366,
            3.556145
        ],
        [
            51.290295,
            3.555932
        ],
        [
            51.296042,
            3.547488
        ],
        [
            51.298266,
            3.527067
        ],
        [
            51.302727,
            3.528449
        ],
        [
            51.310746,
            3.538465
        ],
        [
            51.315567,
            3.528445
        ],
        [
            51.319887,
            3.528821
        ],
        [
            51.3266,
            3.524397
        ],
        [
            51.328151,
            3.521356
        ],
        [
            51.333097,
            3.533906
        ],
        [
            51.339804,
            3.550687
        ]
    ]
,"aangrenzende":["BU17140209","BU17140509","BU17141209","BU17141309","BU17141400"]}]