[{
    "id": "BU17020200",
    "name": "Westerbeek",
    "geoType": "BU",
    "gemeentecode": "1702",
    "wijkcode": "02",
    "buurtcode": "00",
    "polygon": [
        [
            51.582522,
            5.86842
        ],
        [
            51.580581,
            5.86359
        ],
        [
            51.581335,
            5.860253
        ],
        [
            51.57987,
            5.856924
        ],
        [
            51.581213,
            5.855831
        ],
        [
            51.583553,
            5.859439
        ],
        [
            51.585941,
            5.866175
        ],
        [
            51.583981,
            5.869054
        ],
        [
            51.582522,
            5.86842
        ]
    ]
,"aangrenzende":["BU17020209"]}]